stulib/__init__.py
stulib/compute.py
stulib/greeting.py
stulib/web_parser.py
stulib-0.0.4.dist-info/LICENSE
stulib-0.0.4.dist-info/METADATA
stulib-0.0.4.dist-info/WHEEL
stulib-0.0.4.dist-info/top_level.txt
stulib-0.0.4.dist-info/RECORD
