Metadata-Version: 2.1
Name: stulib
Version: 0.0.4
Summary: STU Standard Library
Home-page: https://github.com/javakung/stulib
Author: javakung
Author-email: javakung@gmail.com
License: UNKNOWN
Platform: UNKNOWN
Classifier: Programming Language :: Python :: 3
Classifier: Programming Language :: Python :: 3.8
